CHANGELOG.txt
LICENCE.txt
MANIFEST.in
README.txt
setup.py
pyguard/__init__.py
pyguard/pyguard.py
pyguard.egg-info/SOURCES.txt
pyguard.egg-info/dependency_links.txt
pyguard.egg-info/requires.txt
pyguard.egg-info/top_level.txt
pyguard42.egg-info/PKG-INFO
pyguard42.egg-info/SOURCES.txt
pyguard42.egg-info/dependency_links.txt
pyguard42.egg-info/entry_points.txt
pyguard42.egg-info/requires.txt
pyguard42.egg-info/top_level.txt