Metadata-Version: 1.2
Name: pyguard42
Version: 0.0.6
Summary: auto-starter for python,javascript and cpp codes
Home-page: UNKNOWN
Author: Mevlüt Kaan Karakoç
Author-email: karakockaan326@gmail.com
License: MIT
Project-URL: Github, https://www.github.com/kaankarakoc42/pyguard42
Keywords: auto-starter
Platform: UNKNOWN
Classifier: Development Status :: 5 - Production/Stable
Classifier: Intended Audience :: Education
Classifier: Operating System :: Microsoft :: Windows :: Windows 10
Classifier: License :: OSI Approved :: MIT License
Classifier: Programming Language :: Python :: 3
